epflutils
