Metadata-Version: 1.1
Name: django-epfl-utils
Version: 0.0.3
Summary: A simple Django app to provide tools common to several applications at EPFL.
Home-page: https://charmier@git.epfl.ch/repo/django-utils-epfl.git
Author: Charmier Grégory
Author-email: gregory.charmier@epfl.ch
License: LGPLv3
Platform: UNKNOWN
Classifier: Environment :: Web Environment
Classifier: Framework :: Django
Classifier: Framework :: Django :: 1.8
Classifier: Intended Audience :: Developers
Classifier: License :: OSI Approved :: BSD License
Classifier: Operating System :: OS Independent
Classifier: Programming Language :: Python
Classifier: Programming Language :: Python :: 2.7
Classifier: Topic :: Internet :: WWW/HTTP
Classifier: Topic :: Internet :: WWW/HTTP :: Dynamic Content
